byted_overpass_life_gen_ai_lai_rag/__init__.py
byted_overpass_life_gen_ai_lai_rag-0.0.1.dist-info/METADATA
byted_overpass_life_gen_ai_lai_rag-0.0.1.dist-info/WHEEL
byted_overpass_life_gen_ai_lai_rag-0.0.1.dist-info/top_level.txt
byted_overpass_life_gen_ai_lai_rag-0.0.1.dist-info/RECORD
